ahb_master/rtl/ahb_master_pipeline.v
// ============================================================================
// This is the core AHB pipeline.
// => ADDRESS_GENERATOR_UNIT => DATA_OUT => DATA_IN =>
//    (AGU)                     (DO)        (DI) 
//
// Set WDT to either 32 or 64. That sets the data bus width. When synthesized
// for ASIC, tools can efficiently infer clock gating. Helps for FPGA too. 
// ----------------------------------------------------------------------------
// MIT License.
// (C)2016 Revanth Kamaraj.
// ============================================================================

`default_nettype none

module ahb_pipeline #(parameter WDT = 32'd32, parameter MASTER_ID = 4) 
                                                // Bus width = 32-bit by default.
                                                // Set either 32-bit or 64-bit.
(
        // ==================================
        // AHB Inputs. 
        // ==================================
       
        input   wire            i_hclk,
        input   wire            i_hreset_n,

        input   wire            i_hready,
        input   wire            i_hgrant,
        input   wire [WDT-1:0]  i_hrdata,

        // =================================
        // Pipeline inputs.
        // =================================

        input   wire            i_hwrite,
        input   wire [1:0]      i_hresp,
        input   wire [WDT-1:0]  i_hwdata,
        input   wire [31:0]     i_haddr,
        input   wire [1:0]      i_htrans,
        input   wire [1:0]      i_hsize,
        input   wire [3:0]      i_hprot,
        input   wire            i_hlock,
        input   wire            i_hbusreq,
        input   wire [3:0]      i_hmaster,

        // =================================
        // Pipeline registers / AHB Outputs.
        // =================================

        output  reg  [WDT-1:0]  o_agu_hwdata,
        output  reg  [31:0]     o_agu_haddr,
        output  reg  [1:0]      o_agu_htrans,
        output  reg  [1:0]      o_agu_hsize,
        output  reg  [3:0]      o_agu_hprot,
        output  reg             o_agu_hwrite,
        output  reg             o_agu_hlock,
        output  reg             o_agu_hbusreq,

        output  reg  [WDT-1:0]  o_do_hwdata,
        output  reg  [31:0]     o_do_haddr,
        output  reg  [1:0]      o_do_htrans,
        output  reg  [1:0]      o_do_hsize,
        output  reg  [3:0]      o_do_hprot,
        output  reg             o_do_hwrite,
        output  reg             o_do_hlock,

        output  reg  [WDT-1:0]  o_di_data,
        output  reg             o_di_dav,

        output  wire            o_dontsleep
);

localparam [1:0] IDLE = 2'd0;
localparam [1:0] BUSY = 2'd1;

localparam [1:0] OKAY = 2'd0;
localparam [1:0] ERROR = 2'd1;

// Nosleep flop.
reg dontsleep;
assign o_dontsleep = dontsleep;

// Pipeline anti-stall signal, hwdata anti-stall signal, di_data_en anti-stall.
wire adv = i_hready && (i_hmaster == MASTER_ID);

wire do_hwdata_en = adv                  && 
                    o_agu_hwrite         && 
                   (o_agu_htrans != IDLE || dontsleep) &&
                    o_agu_htrans != BUSY;

wire di_data_en  =  adv                 && 
                    !o_do_hwrite        && 
                    o_do_htrans != IDLE && 
                    o_do_htrans != BUSY;

// Address Generation Unit Stage.
always @ (posedge i_hclk or negedge i_hreset_n)
begin: agu
        if ( !i_hreset_n )
        begin
                o_agu_hwdata    <=      {WDT{1'd0}};
                o_agu_haddr     <=      {WDT{1'd0}};
                o_agu_hsize     <=      2'd0;
                o_agu_hprot     <=      4'd0;
                o_agu_hwrite    <=      1'd1;
                o_agu_hlock     <=      1'd0;
                o_agu_hbusreq   <=      1'd0;
        end               
        else if ( adv )
        begin
                o_agu_hwdata    <=   i_hwdata;    
                o_agu_haddr     <=   i_haddr;     
                o_agu_hsize     <=   i_hsize;     
                o_agu_hprot     <=   i_hprot;     
                o_agu_hwrite    <=   i_hwrite;    
                o_agu_hlock     <=   i_hlock;     
                o_agu_hbusreq   <=   i_hbusreq;   
        end 
end

// Address Generation Unit Stage.
always @ (posedge i_hclk or negedge i_hreset_n)
begin
        if ( !i_hreset_n )
        begin
                o_agu_htrans    <=      IDLE;
                dontsleep       <=      1'd0;
        end
        else if ( i_hgrant && !i_hready && i_hresp != OKAY && i_hresp != ERROR )
        begin
                o_agu_htrans    <=      IDLE;
                dontsleep       <=      1'd1;
        end
        else if ( adv )
        begin
                o_agu_htrans    <=      i_htrans;
                dontsleep       <=      1'd0;
        end
end

// Data Out Stage.
always @ (posedge i_hclk or negedge i_hreset_n)
begin: _do
        if ( !i_hreset_n )
        begin
                o_do_haddr     <=      {WDT{1'd0}};
                o_do_htrans    <=      2'd0;
                o_do_hsize     <=      2'd0;
                o_do_hprot     <=      4'd0;
                o_do_hwrite    <=      1'd1;
                o_do_hlock     <=      1'd0;
        end
        else if ( adv )
        begin
                o_do_haddr     <=   o_agu_haddr;     
                o_do_htrans    <=   o_agu_htrans;    
                o_do_hsize     <=   o_agu_hsize;     
                o_do_hprot     <=   o_agu_hprot;     
                o_do_hwrite    <=   o_agu_hwrite;    
                o_do_hlock     <=   o_agu_hlock;     
        end
end

// Data Out Stage.
always @ (posedge i_hclk or negedge i_hreset_n)
begin: _do_hwdata
        if ( !i_hreset_n )
        begin
                o_do_hwdata     <= {WDT{1'd0}};
        end
        else if ( do_hwdata_en )
        begin
                o_do_hwdata     <= o_agu_hwdata;
        end
end

// Data In Stage.
always @ (posedge i_hclk or negedge i_hreset_n)
begin: di
        if ( !i_hreset_n )
        begin
                o_di_data      <=       {WDT{1'd0}};
        end
        else if ( di_data_en )
        begin
                o_di_data       <=      i_hrdata;
        end
end

// Data In Stage.
always @ (posedge i_hclk or negedge i_hreset_n)
begin: di_dav
        if ( !i_hreset_n ) 
        begin
                o_di_dav <= 1'd0;
        end
        else
        begin               
                o_di_dav <= di_data_en;
        end
end

endmodule

ahb_master/rtl/ahb_master.v
// ============================================================================
// This is the top module. Also contains pipeline control logic. You can set
// data bus to either 32-bit or 64-bit by setting BUS_WDT to either 32 or 64.
//
// WARNING: This design is still very *experimental*. Use it at your own risk.
//
// ----------------------------------------------------------------------------
// MIT License.
// (C)2016 Revanth Kamaraj.
// ============================================================================

`default_nettype none

module ahb_master 
        #( 
                parameter [31:0] BUS_WDT   = 32, 
                parameter [3:0]  MASTER_ID = 4 
        ) 
(
        // =====================================
        // AHB signals. 
        // =====================================
        input   wire                    i_hclk,
        input   wire                    i_hreset_n,

        input   wire                    i_hready,
        input   wire                    i_hgrant,
        input   wire [BUS_WDT-1:0]      i_hrdata,
        input   wire [1:0]              i_hresp,
        input   wire [3:0]              i_hmaster,

        output  wire [BUS_WDT-1:0]      o_hwdata,
        output  wire [31:0]             o_haddr,
        output  wire [1:0]              o_htrans,
        output  wire [1:0]              o_hburst,
        output  wire [1:0]              o_hsize,
        output  wire [3:0]              o_hprot,
        output  wire                    o_hwrite,
        output  wire                    o_hlock,
        output  wire                    o_hbusreq,

        // =====================================
        // UI
        // =====================================
        input   wire [BUS_WDT-1:0]      i_xfer_wdata,
        input   wire [31:0]             i_xfer_addr,
        input   wire [1:0]              i_xfer_size,
        input   wire                    i_xfer_dav,
        input   wire                    i_xfer_trig,
        input   wire                    i_xfer_en,
        input   wire                    i_xfer_write,
        input   wire [3:0]              i_xfer_prot,
        input   wire                    i_xfer_lock,
        input   wire                    i_xfer_full,

        output  wire                    o_xfer_adv,   // Advance UI Combo.        
        output  wire [BUS_WDT-1:0]      o_xfer_rdata,
        output  wire                    o_xfer_rdav,
        output  wire                    o_xfer_ok_to_shutdown
);

localparam [1:0] INCR   = 2'd1;
localparam [1:0] IDLE   = 2'd0;
localparam [1:0] BUSY   = 2'd1;
localparam [1:0] NONSEQ = 2'd2;
localparam [1:0] SEQ    = 2'd3;
localparam [1:0] RETRY  = 2'd2;
localparam [1:0] SPLIT  = 2'd3;

// =========================
// Pipeline inputs.
// =========================

reg                     hwrite;
reg [BUS_WDT-1:0]       hwdata;
reg [31:0]              haddr;
reg [1:0]               htrans;
reg [1:0]               hsize;
reg [3:0]               hprot;
reg                     hlock;
reg                     hbusreq;

// ==========================
// Backtrack taps.
// ==========================

wire [31:0]     do_haddr;
wire [1:0]      do_htrans;
wire [1:0]      do_hsize;
wire [3:0]      do_hprot;
wire            do_hwrite;
wire            do_hlock;
wire            dontsleep; // Not really a backtrack tap but just included.
wire            agu_hbusreq;

// ==========================
// Registers.
// ==========================

reg backtrack_ff;
reg nready_ff;

// ==========================
// Assign
// ==========================
assign o_hburst = INCR;

wire nready =     ( i_xfer_write && !i_xfer_dav   ) || 
                  (!i_xfer_write && !i_xfer_full  );

assign  o_xfer_adv =    i_hready                 && 
                        (i_hmaster == MASTER_ID) && 
                        !backtrack_ff            &&
                        i_hresp != SPLIT         && 
                        i_hresp != RETRY;

assign  o_xfer_ok_to_shutdown = (o_htrans == IDLE && do_htrans == IDLE && 
                                                                !dontsleep);

// Bus request generation.
assign        o_hbusreq = agu_hbusreq | i_xfer_en; 

// ==========================
// Pipeline instance.
// ==========================

ahb_pipeline #(
.WDT(BUS_WDT), .MASTER_ID(MASTER_ID)
) 
        u_ahb_pipeline 
(
// Clock and reset.
.i_hclk         (       i_hclk          ),
.i_hreset_n     (       i_hreset_n      ),

// AHB Inputs.
.i_hready       (       i_hready        ),
.i_hgrant       (       i_hgrant        ),
.i_hrdata       (       i_hrdata        ),
.i_hresp        (       i_hresp         ),
.i_hmaster      (       i_hmaster       ),

// Pipeline inputs.
.i_hwrite       (       hwrite          ),
.i_hwdata       (       hwdata          ),
.i_haddr        (       haddr           ),
.i_htrans       (       htrans          ),
.i_hsize        (       hsize           ),
.i_hprot        (       hprot           ),
.i_hlock        (       hlock           ),
.i_hbusreq      (       hbusreq         ),

// AHB Outputs.
.o_agu_hwdata   (                       ), // UNCONNECTED
.o_agu_haddr    (       o_haddr         ),
.o_agu_htrans   (       o_htrans        ),
.o_agu_hsize    (       o_hsize         ),
.o_agu_hprot    (       o_hprot         ),
.o_agu_hwrite   (       o_hwrite        ),
.o_agu_hlock    (       o_hlock         ),
.o_agu_hbusreq  (       agu_hbusreq     ),

// Backtrack taps.
.o_do_hwdata    (       o_hwdata        ),
.o_do_haddr     (       do_haddr        ),
.o_do_htrans    (       do_htrans       ),
.o_do_hsize     (       do_hsize        ), 
.o_do_hprot     (       do_hprot        ),
.o_do_hwrite    (       do_hwrite       ),
.o_do_hlock     (       do_hlock        ),

// Data Outputs.
.o_di_data      (       o_xfer_rdata    ),
.o_di_dav       (       o_xfer_rdav     ),

// Dontsleep
.o_dontsleep    (       dontsleep       )
);

// =============================
// Combinational logic
// =============================
always @*
begin
        if ( !i_xfer_en && o_xfer_ok_to_shutdown )
        begin
                haddr  = o_haddr;
                hwrite = o_hwrite;
                hwdata = o_hwdata;
                htrans = IDLE;
                hsize  = o_hsize;
                hprot  = o_hprot;
                hbusreq = 1'd0;
                hlock   = 1'd0;
        end
        else if ( i_hresp == RETRY || i_hresp == SPLIT || backtrack_ff )
        begin
                haddr   =       do_haddr;
                hwrite  =       do_hwrite;
                hlock   =       do_hlock;
                hwdata  =       o_hwdata;
                htrans  =       NONSEQ;
                hsize   =       do_hsize;
                hprot   =       do_hprot;
                hbusreq =       1'd1;
        end
        else if ( i_xfer_trig )
        begin
                haddr   =       i_xfer_addr;                
                hwrite  =       i_xfer_write;
                hlock   =       i_xfer_lock;
                hwdata  =       i_xfer_wdata;
                htrans  =       nready ? IDLE : NONSEQ;
                hsize   =       i_xfer_size;
                hprot   =       i_xfer_prot;
                hbusreq =       1'd1;
        end
        else
        begin
                haddr   =       o_haddr +  (nready == 1'd1 ? 32'd0 : 
                                          do_hsize == 2'd0 ? 32'd1 :
                                          do_hsize == 2'd1 ? 32'd2 :
                                          do_hsize == 2'd2 ? 32'd4 : 
                                                             32'd8 );
                hwrite  =       do_hwrite;
                hwdata  =       o_hwdata;
                htrans  =       nready ? BUSY : 
                                        nready_ff ? NONSEQ : 
                                        (o_haddr[31:10] != haddr[31:10]) ? 
                                        NONSEQ : SEQ;

                hwdata  =       i_xfer_wdata;
                hsize   =       do_hsize;
                hlock   =       do_hlock;
                hprot   =       do_hprot;
                hbusreq =       1'd1;
        end
end

// ===============================
// Sequential Logic.
// ===============================
always @ (posedge i_hclk or negedge i_hreset_n)
begin
        if ( !i_hreset_n )
        begin
                backtrack_ff <= 1'd0;
        end
        else if ( ( i_hresp == RETRY || i_hresp == SPLIT ) && 
                    i_hready && i_hgrant )
        begin
                backtrack_ff <= 1'd1;
        end
        else if ( i_hready && i_hgrant )
        begin
                backtrack_ff <= 1'd0;
        end
end

always @ (posedge i_hclk or negedge i_hreset_n)
begin
        if(!i_hreset_n)
        begin
                nready_ff <= 1'd0;
        end
        else if ( i_hready && i_hgrant )
        begin
                nready_ff <= nready;
        end
end

endmodule

ahb_master/bench/ahb_master_test.sv
module ahb_master_test;

parameter BUS_WDT = 32;

// =====================================
// AHB signals. 
// =====================================
bit                       i_hclk;
bit                       i_hreset_n;

bit                       i_hready;
bit                       i_hgrant;
bit    [BUS_WDT-1:0]      i_hrdata;
bit    [1:0]              i_hresp;
bit     [3:0]             i_hmaster;

logic   [BUS_WDT-1:0]      o_hwdata;
logic   [31:0]             o_haddr;
logic   [1:0]              o_htrans;
logic   [1:0]              o_hburst;
logic   [1:0]              o_hsize;
logic   [3:0]              o_hprot;
logic                      o_hwrite;
logic                      o_hlock;
logic                      o_hbusreq;

// =====================================
// UI
// =====================================
logic  [BUS_WDT-1:0]      i_xfer_wdata;
bit    [31:0]             i_xfer_addr;
bit    [1:0]              i_xfer_size;
bit                       i_xfer_dav;
bit                       i_xfer_trig;
bit                       i_xfer_en;
bit                       i_xfer_write;
bit    [3:0]              i_xfer_prot;
bit                       i_xfer_lock;
bit                       i_xfer_full;

logic                      o_xfer_adv;   // Advance UI Combo.        
logic   [BUS_WDT-1:0]      o_xfer_rdata;
logic                      o_xfer_rdav;
logic                      o_xfer_ok_to_shutdown;

ahb_master #(.BUS_WDT(BUS_WDT), .MASTER_ID(0)) u_ahb_master (.*);

always #10 i_hclk++;

initial
begin
        $dumpfile("ahb_master.vcd");
        $dumpvars;

       @(posedge i_hclk);
        i_hreset_n <= 1'd0; 

        @(posedge i_hclk);
        i_xfer_en <= 1'd1;

        repeat(50)
        @(posedge i_hclk);

        @(posedge i_hclk);
        i_hgrant <= 1'd1;
        i_hreset_n <= 1'd1;

        @(posedge i_hclk);
        i_xfer_en    <= 1'd1;
        i_xfer_trig  <= 1'd1;
        i_xfer_write <= 1'd1;
        i_xfer_wdata <= $random;
        i_xfer_addr  <= 32'h2000_0000;
        i_xfer_dav   <= 1'd1;
        i_hready     <= 1'd1;

        @(posedge i_hclk);
        i_xfer_wdata <= $random;
        i_xfer_trig  <= 1'd0;

        @(posedge i_hclk);
        i_hready     <= 1'd1;
        i_xfer_wdata <= $random;

        @(posedge i_hclk);
        i_hresp      <= 2'd3;
        i_hready     <= 1'd0;
        i_xfer_wdata <= $random;

        @(posedge i_hclk);
        i_hresp      <= 2'd3;
        i_hready     <= 1'd0;

        @(posedge i_hclk);
        i_hresp      <= 2'd3;
        i_hready     <= 1'd1;

        @(posedge i_hclk);
        i_hresp      <= 2'd0;
        i_hready     <= 1'd1;

        @(posedge i_hclk);

        @(posedge i_hclk);
        i_xfer_wdata  <= $random;
        i_xfer_dav   <= 1'd1;

        fork
        
                repeat(10) 
                begin
                        @(posedge i_hclk);
                        i_xfer_trig <= 1'd1;
                        i_xfer_dav  <= 1'd0;
                end

                begin
                        repeat(3) @(posedge i_hclk);
                        i_xfer_en <= 1'd0;
                end
        join

        $finish;
end

task delay (int x);
        repeat(x) @(posedge i_hclk);
endtask

endmodule

ahb_master/run/ahb_master.vcd
$date
	Fri Dec 30 10:41:14 2016
$end
$version
	Icarus Verilog
$end
$timescale
	1s
$end
$scope module ahb_master_test $end
$var wire 2 ! o_hburst [1:0] $end
$var wire 1 " o_xfer_rdav $end
$var wire 32 # o_xfer_rdata [31:0] $end
$var wire 1 $ o_xfer_ok_to_shutdown $end
$var wire 1 % o_xfer_adv $end
$var wire 1 & o_hwrite $end
$var wire 32 ' o_hwdata [31:0] $end
$var wire 2 ( o_htrans [1:0] $end
$var wire 2 ) o_hsize [1:0] $end
$var wire 4 * o_hprot [3:0] $end
$var wire 1 + o_hlock $end
$var wire 1 , o_hbusreq $end
$var wire 32 - o_haddr [31:0] $end
$var reg 32 . i_xfer_wdata [31:0] $end
$var reg 1 / i_hclk $end
$var reg 1 0 i_hgrant $end
$var reg 4 1 i_hmaster [3:0] $end
$var reg 32 2 i_hrdata [31:0] $end
$var reg 1 3 i_hready $end
$var reg 1 4 i_hreset_n $end
$var reg 2 5 i_hresp [1:0] $end
$var reg 32 6 i_xfer_addr [31:0] $end
$var reg 1 7 i_xfer_dav $end
$var reg 1 8 i_xfer_en $end
$var reg 1 9 i_xfer_full $end
$var reg 1 : i_xfer_lock $end
$var reg 4 ; i_xfer_prot [3:0] $end
$var reg 2 < i_xfer_size [1:0] $end
$var reg 1 = i_xfer_trig $end
$var reg 1 > i_xfer_write $end
$scope module u_ahb_master $end
$var wire 1 / i_hclk $end
$var wire 1 0 i_hgrant $end
$var wire 4 ? i_hmaster [3:0] $end
$var wire 32 @ i_hrdata [31:0] $end
$var wire 1 3 i_hready $end
$var wire 1 4 i_hreset_n $end
$var wire 2 A i_hresp [1:0] $end
$var wire 32 B i_xfer_addr [31:0] $end
$var wire 1 7 i_xfer_dav $end
$var wire 1 8 i_xfer_en $end
$var wire 1 9 i_xfer_full $end
$var wire 1 : i_xfer_lock $end
$var wire 4 C i_xfer_prot [3:0] $end
$var wire 2 D i_xfer_size [1:0] $end
$var wire 1 = i_xfer_trig $end
$var wire 32 E i_xfer_wdata [31:0] $end
$var wire 1 > i_xfer_write $end
$var wire 1 F nready $end
$var wire 2 G o_hburst [1:0] $end
$var wire 1 , o_hbusreq $end
$var wire 1 % o_xfer_adv $end
$var wire 1 $ o_xfer_ok_to_shutdown $end
$var wire 1 " o_xfer_rdav $end
$var wire 32 H o_xfer_rdata [31:0] $end
$var wire 1 & o_hwrite $end
$var wire 32 I o_hwdata [31:0] $end
$var wire 2 J o_htrans [1:0] $end
$var wire 2 K o_hsize [1:0] $end
$var wire 4 L o_hprot [3:0] $end
$var wire 1 + o_hlock $end
$var wire 32 M o_haddr [31:0] $end
$var wire 1 N dontsleep $end
$var wire 1 O do_hwrite $end
$var wire 2 P do_htrans [1:0] $end
$var wire 2 Q do_hsize [1:0] $end
$var wire 4 R do_hprot [3:0] $end
$var wire 1 S do_hlock $end
$var wire 32 T do_haddr [31:0] $end
$var wire 1 U agu_hbusreq $end
$var reg 1 V backtrack_ff $end
$var reg 32 W haddr [31:0] $end
$var reg 1 X hbusreq $end
$var reg 1 Y hlock $end
$var reg 4 Z hprot [3:0] $end
$var reg 2 [ hsize [1:0] $end
$var reg 2 \ htrans [1:0] $end
$var reg 32 ] hwdata [31:0] $end
$var reg 1 ^ hwrite $end
$var reg 1 _ nready_ff $end
$scope module u_ahb_pipeline $end
$var wire 1 ` adv $end
$var wire 1 a di_data_en $end
$var wire 1 b do_hwdata_en $end
$var wire 32 c i_haddr [31:0] $end
$var wire 1 X i_hbusreq $end
$var wire 1 / i_hclk $end
$var wire 1 0 i_hgrant $end
$var wire 1 Y i_hlock $end
$var wire 4 d i_hmaster [3:0] $end
$var wire 4 e i_hprot [3:0] $end
$var wire 32 f i_hrdata [31:0] $end
$var wire 1 3 i_hready $end
$var wire 1 4 i_hreset_n $end
$var wire 2 g i_hresp [1:0] $end
$var wire 2 h i_hsize [1:0] $end
$var wire 2 i i_htrans [1:0] $end
$var wire 32 j i_hwdata [31:0] $end
$var wire 1 ^ i_hwrite $end
$var wire 1 N o_dontsleep $end
$var reg 1 k dontsleep $end
$var reg 32 l o_agu_haddr [31:0] $end
$var reg 1 U o_agu_hbusreq $end
$var reg 1 + o_agu_hlock $end
$var reg 4 m o_agu_hprot [3:0] $end
$var reg 2 n o_agu_hsize [1:0] $end
$var reg 2 o o_agu_htrans [1:0] $end
$var reg 32 p o_agu_hwdata [31:0] $end
$var reg 1 & o_agu_hwrite $end
$var reg 32 q o_di_data [31:0] $end
$var reg 1 " o_di_dav $end
$var reg 32 r o_do_haddr [31:0] $end
$var reg 1 S o_do_hlock $end
$var reg 4 s o_do_hprot [3:0] $end
$var reg 2 t o_do_hsize [1:0] $end
$var reg 2 u o_do_htrans [1:0] $end
$var reg 32 v o_do_hwdata [31:0] $end
$var reg 1 O o_do_hwrite $end
$scope begin _do $end
$upscope $end
$scope begin _do_hwdata $end
$upscope $end
$scope begin agu $end
$upscope $end
$scope begin di $end
$upscope $end
$scope begin di_dav $end
$upscope $end
$upscope $end
$upscope $end
$scope task delay $end
$var integer 32 w x [31:0] $end
$upscope $end
$upscope $end
$enddefinitions $end
#0
$dumpvars
b0 w
bx v
bx u
bx t
bx s
bx r
bx q
bx p
bx o
bx n
bx m
bx l
xk
bx j
b1 i
bx h
b0 g
b0 f
bx e
b0 d
bx c
0b
0a
0`
x_
x^
bx ]
b1 \
bx [
bx Z
xY
1X
bx W
xV
xU
bx T
xS
bx R
bx Q
bx P
xO
xN
bx M
bx L
bx K
bx J
bx I
bx H
b1 G
1F
bx E
b0 D
b0 C
b0 B
b0 A
b0 @
b0 ?
0>
0=
b0 <
b0 ;
0:
09
08
07
b0 6
b0 5
04
03
b0 2
b0 1
00
0/
bx .
bx -
x,
x+
bx *
bx )
bx (
bx '
x&
0%
x$
bx #
x"
b1 !
$end
#10
0X
b0 \
b0 i
0,
1$
b0 Z
b0 e
0Y
b0 [
b0 h
b0 ]
b0 j
1^
b0 W
b0 c
0"
b0 #
b0 H
b0 q
b0 '
b0 I
b0 v
0S
1O
b0 R
b0 s
b0 Q
b0 t
b0 P
b0 u
b0 T
b0 r
0U
0+
1&
b0 *
b0 L
b0 m
b0 )
b0 K
b0 n
b0 -
b0 M
b0 l
b0 p
0N
0k
b0 (
b0 J
b0 o
0V
0_
1/
#20
0/
#30
1,
1X
bx ]
bx j
b1 \
b1 i
18
1/
#40
0/
#50
1/
#60
0/
#70
1/
#80
0/
#90
1/
#100
0/
#110
1/
#120
0/
#130
1/
#140
0/
#150
1/
#160
0/
#170
1/
#180
0/
#190
1/
#200
0/
#210
1/
#220
0/
#230
1/
#240
0/
#250
1/
#260
0/
#270
1/
#280
0/
#290
1/
#300
0/
#310
1/
#320
0/
#330
1/
#340
0/
#350
1/
#360
0/
#370
1/
#380
0/
#390
1/
#400
0/
#410
1/
#420
0/
#430
1/
#440
0/
#450
1/
#460
0/
#470
1/
#480
0/
#490
1/
#500
0/
#510
1/
#520
0/
#530
1/
#540
0/
#550
1/
#560
0/
#570
1/
#580
0/
#590
1/
#600
0/
#610
1/
#620
0/
#630
1/
#640
0/
#650
1/
#660
0/
#670
1/
#680
0/
#690
1/
#700
0/
#710
1/
#720
0/
#730
1/
#740
0/
#750
1/
#760
0/
#770
1/
#780
0/
#790
1/
#800
0/
#810
1/
#820
0/
#830
1/
#840
0/
#850
1/
#860
0/
#870
1/
#880
0/
#890
1/
#900
0/
#910
1/
#920
0/
#930
1/
#940
0/
#950
1/
#960
0/
#970
1/
#980
0/
#990
1/
#1000
0/
#1010
1/
#1020
0/
#1030
1/
#1040
0/
#1050
14
10
1/
#1060
0/
#1070
1%
0F
1`
b10 \
b10 i
b10010000101010011010100100100 ]
b10010000101010011010100100100 j
b100000000000000000000000000000 W
b100000000000000000000000000000 c
13
17
b100000000000000000000000000000 6
b100000000000000000000000000000 B
b10010000101010011010100100100 .
b10010000101010011010100100100 E
1>
1=
1/
#1080
0/
#1090
1b
0$
b11 \
b11 i
b11000000100010010101111010000001 ]
b11000000100010010101111010000001 j
b100000000000000000000000000001 W
b100000000000000000000000000001 c
1U
b100000000000000000000000000000 -
b100000000000000000000000000000 M
b100000000000000000000000000000 l
b10010000101010011010100100100 p
b10 (
b10 J
b10 o
0=
b11000000100010010101111010000001 .
b11000000100010010101111010000001 E
1/
#1100
0/
#1110
b10000100100001001101011000001001 ]
b10000100100001001101011000001001 j
b100000000000000000000000000010 W
b100000000000000000000000000010 c
b10010000101010011010100100100 '
b10010000101010011010100100100 I
b10010000101010011010100100100 v
b10 P
b10 u
b100000000000000000000000000000 T
b100000000000000000000000000000 r
b100000000000000000000000000001 -
b100000000000000000000000000001 M
b100000000000000000000000000001 l
b11000000100010010101111010000001 p
b11 (
b11 J
b11 o
b10000100100001001101011000001001 .
b10000100100001001101011000001001 E
1/
#1120
0/
#1130
0b
0%
0`
b10 \
b10 i
b11000000100010010101111010000001 ]
b11000000100010010101111010000001 j
b100000000000000000000000000001 W
b100000000000000000000000000001 c
b11000000100010010101111010000001 '
b11000000100010010101111010000001 I
b11000000100010010101111010000001 v
b11 P
b11 u
b100000000000000000000000000001 T
b100000000000000000000000000001 r
b100000000000000000000000000010 -
b100000000000000000000000000010 M
b100000000000000000000000000010 l
b10000100100001001101011000001001 p
b10110001111100000101011001100011 .
b10110001111100000101011001100011 E
03
b11 5
b11 A
b11 g
1/
#1140
0/
#1150
1N
1k
b0 (
b0 J
b0 o
1/
#1160
0/
#1170
1b
1`
13
1/
#1180
0/
#1190
0%
b10000100100001001101011000001001 ]
b10000100100001001101011000001001 j
b100000000000000000000000000010 W
b100000000000000000000000000010 c
b10000100100001001101011000001001 '
b10000100100001001101011000001001 I
b10000100100001001101011000001001 v
b0 P
b0 u
b100000000000000000000000000010 T
b100000000000000000000000000010 r
b100000000000000000000000000001 -
b100000000000000000000000000001 M
b100000000000000000000000000001 l
b11000000100010010101111010000001 p
1V
0N
0k
b10 (
b10 J
b10 o
b0 5
b0 A
b0 g
1/
#1200
0/
#1210
1%
b11 \
b11 i
b10110001111100000101011001100011 ]
b10110001111100000101011001100011 j
b100000000000000000000000000011 W
b100000000000000000000000000011 c
b11000000100010010101111010000001 '
b11000000100010010101111010000001 I
b11000000100010010101111010000001 v
b10 P
b10 u
b100000000000000000000000000001 T
b100000000000000000000000000001 r
b100000000000000000000000000010 -
b100000000000000000000000000010 M
b100000000000000000000000000010 l
b10000100100001001101011000001001 p
0V
1/
#1220
0/
#1230
b110101110010111101100001101 ]
b110101110010111101100001101 j
b100000000000000000000000000100 W
b100000000000000000000000000100 c
b10000100100001001101011000001001 '
b10000100100001001101011000001001 I
b10000100100001001101011000001001 v
b100000000000000000000000000010 T
b100000000000000000000000000010 r
b100000000000000000000000000011 -
b100000000000000000000000000011 M
b100000000000000000000000000011 l
b10110001111100000101011001100011 p
b11 (
b11 J
b11 o
b110101110010111101100001101 .
b110101110010111101100001101 E
1/
#1240
0/
#1250
1F
b0 \
b0 i
b100000000000000000000000000000 W
b100000000000000000000000000000 c
b10110001111100000101011001100011 '
b10110001111100000101011001100011 I
b10110001111100000101011001100011 v
b11 P
b11 u
b100000000000000000000000000011 T
b100000000000000000000000000011 r
b100000000000000000000000000100 -
b100000000000000000000000000100 M
b100000000000000000000000000100 l
b110101110010111101100001101 p
07
1=
1/
#1260
0/
#1270
0b
b110101110010111101100001101 '
b110101110010111101100001101 I
b110101110010111101100001101 v
b100000000000000000000000000100 T
b100000000000000000000000000100 r
b100000000000000000000000000000 -
b100000000000000000000000000000 M
b100000000000000000000000000000 l
1_
b0 (
b0 J
b0 o
1/
#1280
0/
#1290
0X
1$
b0 P
b0 u
b100000000000000000000000000000 T
b100000000000000000000000000000 r
08
1/
#1300
0/
#1310
0,
0U
1/
